kognic/query/__init__.py
kognic/query/_version.py
kognic/query/query_api_client.py
kognic/query/query_model.py
kognic/query/util.py
kognic_query-3.0.1.dist-info/METADATA
kognic_query-3.0.1.dist-info/WHEEL
kognic_query-3.0.1.dist-info/top_level.txt
kognic_query-3.0.1.dist-info/RECORD
