Metadata-Version: 2.1
Name: kognic-query
Version: 3.0.1
Summary: Kognic Query
Author-email: Michel Edkrantz <michel.edkrantz@kognic.com>
License: MIT
Project-URL: homepage, https://github.com/annotell/kognic-query-python
Keywords: Kognic,API
Requires-Python: >=3.8
Requires-Dist: requests <3,>=2.20
Requires-Dist: kognic-auth[requests] <4,>=3.0.0
